gwemopt/__init__.py
gwemopt/_version.py
gwemopt/args.py
gwemopt/coverage.py
gwemopt/efficiency.py
gwemopt/lightcurve.py
gwemopt/moc.py
gwemopt/params.py
gwemopt/paths.py
gwemopt/run.py
gwemopt/scheduler.py
gwemopt/segments.py
gwemopt/tiles.py
gwemopt/catalogs/__init__.py
gwemopt/catalogs/base_catalog.py
gwemopt/catalogs/clu.py
gwemopt/catalogs/get.py
gwemopt/catalogs/glade.py
gwemopt/catalogs/mangrove.py
gwemopt/catalogs/nedlvs.py
gwemopt/catalogs/twomrs.py
gwemopt/chipgaps/__init__.py
gwemopt/chipgaps/decam.py
gwemopt/chipgaps/ztf.py
gwemopt/data/config/ATLAS.config
gwemopt/data/config/Abastunami-T48.config
gwemopt/data/config/Abastunami-T70.config
gwemopt/data/config/BlackGEM.config
gwemopt/data/config/C2PU.config
gwemopt/data/config/CFHT.config
gwemopt/data/config/COLIBRI.config
gwemopt/data/config/DDOTI.config
gwemopt/data/config/DECam.config
gwemopt/data/config/F60.config
gwemopt/data/config/FAKE.config
gwemopt/data/config/FZU-Auger.config
gwemopt/data/config/FZU-CTA-N.config
gwemopt/data/config/GIT.config
gwemopt/data/config/GOTO-4.config
gwemopt/data/config/GWAC.config
gwemopt/data/config/Gattini.config
gwemopt/data/config/IRIS.config
gwemopt/data/config/KAO.config
gwemopt/data/config/KPED.config
gwemopt/data/config/LSST.config
gwemopt/data/config/Lisnyky-AZT8.config
gwemopt/data/config/Makes-60.config
gwemopt/data/config/NOWT.config
gwemopt/data/config/Nickel.config
gwemopt/data/config/OAJ.config
gwemopt/data/config/OSN.config
gwemopt/data/config/PS1.config
gwemopt/data/config/Roman.config
gwemopt/data/config/SBO.config
gwemopt/data/config/SOAR-phot.config
gwemopt/data/config/SRO.config
gwemopt/data/config/SVOM-MXT.config
gwemopt/data/config/SVOM-VT.config
gwemopt/data/config/SWOPE.config
gwemopt/data/config/ShAO-2m.config
gwemopt/data/config/ShAO-T60.config
gwemopt/data/config/TCA.config
gwemopt/data/config/TCH.config
gwemopt/data/config/TELESTO.config
gwemopt/data/config/TNT.config
gwemopt/data/config/TRE.config
gwemopt/data/config/UBAI-T60N.config
gwemopt-0.3.6.dist-info/LICENSE
gwemopt-0.3.6.dist-info/METADATA
gwemopt-0.3.6.dist-info/WHEEL
gwemopt-0.3.6.dist-info/entry_points.txt
gwemopt-0.3.6.dist-info/top_level.txt
gwemopt-0.3.6.dist-info/RECORD
