Metadata-Version: 2.1
Name: gwemopt
Version: 0.3.6
Summary: A python package for GW-EM Followup Optimization
Author-email: Michael Coughlin <michael.coughlin@ligo.org>
License: GPLv3
Classifier: Programming Language :: Python :: 3
Classifier: Programming Language :: Python :: 3.10
Classifier: Programming Language :: Python :: 3.11
Classifier: Programming Language :: Python :: 3.12
Classifier: Intended Audience :: Science/Research
Classifier: Intended Audience :: End Users/Desktop
Classifier: Intended Audience :: Developers
Classifier: Natural Language :: English
Classifier: Topic :: Scientific/Engineering
Classifier: Topic :: Scientific/Engineering :: Astronomy
Classifier: Topic :: Scientific/Engineering :: Physics
Classifier: Operating System :: POSIX
Classifier: Operating System :: Unix
Classifier: Operating System :: MacOS
Classifier: License :: OSI Approved :: GNU General Public License v3 (GPLv3)
Requires-Python: >=3.9
License-File: LICENSE
Requires-Dist: numba
Requires-Dist: numpy >=1.7.1
Requires-Dist: scipy >=1.2.1
Requires-Dist: matplotlib >=1.2.0
Requires-Dist: astropy >=1.1.1
Requires-Dist: astropy-healpix
Requires-Dist: python-dateutil
Requires-Dist: mocpy >=0.16.0
Requires-Dist: astroquery
Requires-Dist: astroplan
Requires-Dist: ephem
Requires-Dist: pyyaml
Requires-Dist: joblib
Requires-Dist: ligo-segments
Requires-Dist: ligo.skymap
Requires-Dist: lxml
Requires-Dist: h5py
Requires-Dist: healpy
Requires-Dist: ortools
Requires-Dist: pandas
Requires-Dist: pulp
Requires-Dist: shapely
Requires-Dist: tables
Requires-Dist: regions
Provides-Extra: test
Requires-Dist: pytest ; extra == 'test'
Requires-Dist: pytest-runner ; extra == 'test'
Requires-Dist: pytest-rerunfailures ; extra == 'test'
Requires-Dist: coverage ; extra == 'test'
Requires-Dist: coveralls ; extra == 'test'
Requires-Dist: freezegun ; extra == 'test'
